[
  {
    "id": 1,
    "title": "Sketch",
    "description": "Real-time collaboration platform for teams to brainstorm, design, and build together.",
    "image": "/sketch_sketch_thumb.png",
    "technologies": ["Next.js", "TypeScript", "Monorepo", "Tailwind CSS", "Web Socket", "Node.js", "PostgreSQL"],
    "github": "https://github.com/dheeraj1717/sketch-sketch",
    "demo": "https://sketch-sketch-frontend-aomz.vercel.app/"
  },
  {
    "id": 2,
    "title": "FleetFlow",
    "description": "Modern Fleet Management: Track Clients, Drivers, Vehicles, Jobs, and Streamline Invoicing using Next.js",
    "image": "/t1.png",
    "technologies": ["Next.js", "React", "TypeScript", "Tailwind", "PostgreSQL","JWT"],
    "github": "https://github.com/dheeraj1717/Fleet-Manager",
    "demo": "https://fleet-manager-cq9x.vercel.app/"
  },
  {
    "id": 3,
    "title": "Streamerr",
    "description": "A platform supporting live video streaming using NextJs, React, Prisma, Tailwind, and MongoDB.",
    "image": "/streamerrThumb.png",
    "technologies": ["Next.js", "React", "Prisma", "Tailwind", "MongoDB", "Node.js", "Express.js"],
    "github": "https://github.com/dheeraj1717/streamerr",
    "demo": "https://streamerr.vercel.app/"
  },
  {
    "id": 4,
    "title": "TopicTree",
    "description": "A dynamic post-loading platform created with React.js, Next.js, TypeScript, Prisma, Tailwind CSS, Shadcn UI, and NextAuth.js.",
    "image": "/TopicTree.png",
    "technologies": ["NextJS", "Tailwind CSS", "TypeScript", "Prisma", "Shadcn UI", "NextAuth.js"],
    "github": "https://github.com/dheeraj1717/topic-tree",
    "demo": "https://topic-tree.vercel.app/"
  }
]
  